tipsi_tools/__init__.py
tipsi_tools/logging.py
tipsi_tools/profiler.py
tipsi_tools/python.py
tipsi_tools/unix.py
tipsi_tools/django/__init__.py
tipsi_tools/django/log_requests.py
tipsi_tools/drf/__init__.py
tipsi_tools/drf/filters.py
tipsi_tools/drf/serializers.py
tipsi_tools/scripts/__init__.py
tipsi_tools/scripts/run_filebeat.py
tipsi_tools/scripts/tipsi_ci_script.py
tipsi_tools/scripts/tipsi_env_yaml.py
tipsi_tools/scripts/tipsi_tools_wait.py
tipsi_tools/testing/__init__.py
tipsi_tools/testing/aio.py
tipsi_tools/testing/meta.py
tipsi_tools/testing/drf/__init__.py
tipsi_tools/testing/drf/base.py
tipsi_tools/testing/drf/proxy.py
tipsi_tools-1.10.0.dist-info/DESCRIPTION.rst
tipsi_tools-1.10.0.dist-info/METADATA
tipsi_tools-1.10.0.dist-info/RECORD
tipsi_tools-1.10.0.dist-info/WHEEL
tipsi_tools-1.10.0.dist-info/entry_points.txt
tipsi_tools-1.10.0.dist-info/metadata.json
tipsi_tools-1.10.0.dist-info/top_level.txt
