Metadata-Version: 2.0
Name: tipsi-tools
Version: 1.10.0
Summary: Various python stuff: testing, aio helpers, etc
Home-page: http://github.com/tipsi/tipsi_tools
Author: cybergrind
Author-email: cybergrind@gmail.com
License: UNKNOWN
Keywords: testing,asyncio
Platform: UNKNOWN
Classifier: Development Status :: 4 - Beta
Classifier: Intended Audience :: Developers
Classifier: License :: OSI Approved :: MIT License
Classifier: Operating System :: MacOS
Classifier: Operating System :: MacOS :: MacOS X
Classifier: Operating System :: POSIX
Classifier: Operating System :: POSIX :: Linux
Classifier: Operating System :: Unix
Classifier: Programming Language :: Python
Classifier: Programming Language :: Python :: 3.5
Classifier: Programming Language :: Python :: 3.6
Classifier: Programming Language :: Python :: Implementation
Classifier: Programming Language :: Python :: Implementation :: CPython
Classifier: Topic :: Software Development
Classifier: Topic :: Software Development :: Libraries
Classifier: Topic :: Utilities
Requires-Dist: pyyaml (>=3.12)
Requires-Dist: python-json-logger (>=0.1.5)
